labotools_nysg/__init__.py
labotools_nysg/labotools.py
labotools_nysg-0.0.1.dist-info/METADATA
labotools_nysg-0.0.1.dist-info/WHEEL
labotools_nysg-0.0.1.dist-info/licenses/LICENSE
labotools_nysg-0.0.1.dist-info/RECORD
